triqs_hartree_fock/__init__.py
triqs_hartree_fock/impurity.py
triqs_hartree_fock/lattice.py
triqs_hartree_fock/utils.py
triqs_hartree_fock/version.py
triqs_hartree_fock-3.3.0.dist-info/COPYING.txt
triqs_hartree_fock-3.3.0.dist-info/LICENSE.txt
triqs_hartree_fock-3.3.0.dist-info/METADATA
triqs_hartree_fock-3.3.0.dist-info/WHEEL
triqs_hartree_fock-3.3.0.dist-info/top_level.txt
triqs_hartree_fock-3.3.0.dist-info/RECORD
